autosubb/__init__.py
autosubb/__main__.py
autosubb/constants.py
autosubb/formatters.py
autosub_baidu-0.2.0.dist-info/LICENSE
autosub_baidu-0.2.0.dist-info/METADATA
autosub_baidu-0.2.0.dist-info/WHEEL
autosub_baidu-0.2.0.dist-info/top_level.txt
autosub_baidu-0.2.0.dist-info/RECORD
