Metadata-Version: 2.1
Name: autosub-baidu
Version: 0.2.0
Summary: Auto-generates subtitles for any video or audio file. (Using Baidu AIP)
Home-page: https://github.com/RyouMon/autosub-baidu
Author: RyouMon
Author-email: wenslife@outlook.com
License: UNKNOWN
Project-URL: Bug Tracker, https://github.com/RyouMon/autosub-baidu/issues
Platform: UNKNOWN
Classifier: Programming Language :: Python :: 3
Classifier: License :: OSI Approved :: MIT License
Classifier: Operating System :: OS Independent
Requires-Python: >=3.6
License-File: LICENSE
Requires-Dist: pysrt (==1.1.2)
Requires-Dist: requests (>=2.26.0)
Requires-Dist: progressbar (==2.5)
Requires-Dist: baidu-aip (==2.2.18.0)
